setup.py
hcy_import.egg-info/PKG-INFO
hcy_import.egg-info/SOURCES.txt
hcy_import.egg-info/dependency_links.txt
hcy_import.egg-info/top_level.txt
pkgs/__init__.py
pkgs/utils.py