Metadata-Version: 1.0
Name: hcy-import
Version: 0.1
Summary: easy import
Home-page: http://google.com
Author: hcyangnull
Author-email: hcyangnull@gmail.com
License: UNKNOWN
Platform: UNKNOWN
